ibm_code_engine_sdk/__init__.py
ibm_code_engine_sdk/code_engine_v2.py
ibm_code_engine_sdk/common.py
ibm_code_engine_sdk/ibm_cloud_code_engine_v1.py
ibm_code_engine_sdk/version.py
ibm_code_engine_sdk-4.22.0.dist-info/licenses/LICENSE
ibm_code_engine_sdk-4.22.0.dist-info/METADATA
ibm_code_engine_sdk-4.22.0.dist-info/WHEEL
ibm_code_engine_sdk-4.22.0.dist-info/top_level.txt
ibm_code_engine_sdk-4.22.0.dist-info/zip-safe
ibm_code_engine_sdk-4.22.0.dist-info/RECORD
