Metadata-Version: 2.4
Name: ibm-code-engine-sdk
Version: 4.22.0
Summary: Python SDK for IBM Cloud Code Engine
Home-page: https://github.com/IBM/code-engine-python-sdk
Author: IBM
Author-email: IBM <coligo@de.ibm.com>
License: Apache 2.0
Project-URL: Homepage, https://github.com/IBM/code-engine-python-sdk
Keywords: ibm_code_engine_sdk,ibm-code-engine-sdk,Code Engine,Code-Engine,code engine,code-engine
Classifier: Programming Language :: Python
Classifier: Programming Language :: Python :: 3
Classifier: Programming Language :: Python :: 3.9
Classifier: Programming Language :: Python :: 3.10
Classifier: Programming Language :: Python :: 3.11
Classifier: Programming Language :: Python :: 3.12
Classifier: Programming Language :: Python :: 3.13
Classifier: Development Status :: 5 - Production/Stable
Classifier: Intended Audience :: Developers
Classifier: License :: OSI Approved :: Apache Software License
Classifier: Operating System :: OS Independent
Classifier: Topic :: Software Development :: Libraries :: Python Modules
Classifier: Topic :: Software Development :: Libraries :: Application Frameworks
License-File: LICENSE
Requires-Dist: requests<3.0.0,>=2.32.4
Requires-Dist: urllib3<2.7.0,>=2.6.3
Requires-Dist: python_dateutil<3.0.0,>=2.5.3
Requires-Dist: ibm_cloud_sdk_core<4.0.0,>=3.16.0
Provides-Extra: dev
Requires-Dist: coverage>=4.5.4; extra == "dev"
Requires-Dist: pylint<4.1.0,>=4.0.2; extra == "dev"
Requires-Dist: pytest<9.1.0,>=9.0.0; extra == "dev"
Requires-Dist: pytest-cov<7.1.0,>=7.0.0; extra == "dev"
Requires-Dist: pytest-rerunfailures>=3.1; extra == "dev"
Requires-Dist: responses<1.0.0,>=0.12.1; extra == "dev"
Requires-Dist: black>=26.1.0; extra == "dev"
Dynamic: author
Dynamic: home-page
Dynamic: license-file
